isotp/__init__.py
isotp/address.py
isotp/can_message.py
isotp/errors.py
isotp/protocol.py
isotp/tpsock/__init__.py
isotp/tpsock/opts.py
can_isotp_fork-1.9.dist-info/LICENSE.txt
can_isotp_fork-1.9.dist-info/METADATA
can_isotp_fork-1.9.dist-info/WHEEL
can_isotp_fork-1.9.dist-info/top_level.txt
can_isotp_fork-1.9.dist-info/RECORD
