Metadata-Version: 2.1
Name: can-isotp-fork
Version: 1.9
Summary: Module enabling the IsoTP protocol defined by ISO-15765
License: MIT
Keywords: isotp,can,iso-15765,15765,iso15765
Classifier: Programming Language :: Python
Classifier: Programming Language :: Python :: 3
Classifier: Development Status :: 4 - Beta
Classifier: Operating System :: POSIX :: Linux
Classifier: Intended Audience :: Developers
Classifier: License :: OSI Approved :: MIT License
Classifier: Topic :: Scientific/Engineering :: Interface Engine/Protocol Translator
Requires-Python: >=3.7
License-File: LICENSE.txt
